Metadata-Version: 1.1
Name: dummyapi
Version: 0.3
Summary: Just dummy APIs for Python from Django Rest Framework.
Home-page: http://yeisoncardona.com/
Author: Yeison Cardona
Author-email: yeisoneng@gmail.com
License: BSD License
Download-URL: https://bitbucket.org/yeisoneng/python-dummyapi/downloads
Platform: UNKNOWN
Classifier: Environment :: Web Environment
Classifier: Framework :: Django
